commonroad_control/__init__.py
commonroad_control/control/__init__.py
commonroad_control/control/control.py
commonroad_control/control/model_predictive_control/__init__.py
commonroad_control/control/model_predictive_control/model_predictive_control.py
commonroad_control/control/model_predictive_control/optimal_control/__init__.py
commonroad_control/control/model_predictive_control/optimal_control/optimal_control.py
commonroad_control/control/model_predictive_control/optimal_control/optimal_control_scvx.py
commonroad_control/control/pid/__init__.py
commonroad_control/control/pid/pid_control.py
commonroad_control/control/pid/pid_long_lat.py
commonroad_control/control/reference_trajectory_factory.py
commonroad_control/cr_control_easy_api/__init__.py
commonroad_control/cr_control_easy_api/mpc_for_dedicated_planner.py
commonroad_control/cr_control_easy_api/pid_for_dedicated_planner.py
commonroad_control/planning_converter/__init__.py
commonroad_control/planning_converter/planning_converter_interface.py
commonroad_control/planning_converter/reactive_planner_converter.py
commonroad_control/simulation/__init__.py
commonroad_control/simulation/sensor_models/__init__.py
commonroad_control/simulation/sensor_models/full_state_feedback/__init__.py
commonroad_control/simulation/sensor_models/full_state_feedback/full_state_feedback.py
commonroad_control/simulation/sensor_models/output_interface.py
commonroad_control/simulation/sensor_models/sensor_model_interface.py
commonroad_control/simulation/simulation/__init__.py
commonroad_control/simulation/simulation/simulation.py
commonroad_control/simulation/uncertainty_model/__init__.py
commonroad_control/simulation/uncertainty_model/gaussian_distribution.py
commonroad_control/simulation/uncertainty_model/no_uncertainty.py
commonroad_control/simulation/uncertainty_model/uncertainty_interface.py
commonroad_control/simulation/uncertainty_model/uncertainty_model_interface.py
commonroad_control-0.0.1.dist-info/METADATA
commonroad_control-0.0.1.dist-info/WHEEL
commonroad_control-0.0.1.dist-info/licenses/LICENSE
commonroad_control-0.0.1.dist-info/RECORD
