Metadata-Version: 2.4
Name: commonroad-control
Version: 0.0.1
Summary: CommonRoad Control Toolbox
License: BSD
License-File: LICENSE
Keywords: autonomous,automated,vehicles,driving,control
Author: Lukas Schäfer
Author-email: <lukas.schaefer@tum.de>
Requires-Python: >=3.10, <3.12
Classifier: Programming Language :: Python :: 3.9
Classifier: License :: OSI Approved :: BSD License
Classifier: Operating System :: POSIX :: Linux
Requires-Dist: casadi (>=3.6)
Requires-Dist: clarabel (>=0.9.0)
Requires-Dist: commonroad-io (>=2022.2)
Requires-Dist: cvxpy (==1.6.0)
Requires-Dist: matplotlib (>=3.8)
Requires-Dist: numpy (>=2.1.1,<3.0)
Requires-Dist: scipy (>=1.13)
